{
  "id": 9504,
  "title": "Glengarry Glen Ross",
  "slug": "glengarry-glen-ross",
  "year": "1992",
  "overview": "Times are tough at Premiere Properties. Shelley \"the machine\" Levene and Dave Moss are veteran salesmen, but only Ricky Roma is on a hot streak. The new Glengarry sales leads could turn everything around, but the front office is holding them back until these \"losers\" prove themselves. Then someone decides to take matters into his own hands, stealing the Glengarry leads and leaving everyone wondering who did it.",
  "rating": 7.3,
  "genres": [
    "Crime",
    "Drama",
    "Mystery"
  ],
  "images": [
    "still_0.webp",
    "still_1.webp",
    "still_2.webp"
  ]
}