{
  "id": 431937,
  "title": "Mr & Mme Adelman",
  "slug": "mr-mme-adelman",
  "year": "2017",
  "overview": "How did Sarah and Victor get along for more than 45 years? Who was this enigmatic woman living in the shadow of her husband? Love, ambition, betrayals and secrets feed the story of this extraordinary couple, as they experience both the large and small moments of the last century's history.",
  "rating": 7.464,
  "genres": [
    "Romance",
    "Drama",
    "Comedy"
  ],
  "images": [
    "still_0.webp"
  ]
}