{
  "id": 296096,
  "title": "Me Before You",
  "year": "2016",
  "overview": "A small town girl is caught between dead-end jobs. A high-profile, successful man becomes wheelchair bound following an accident. The man decides his life is not worth living until the girl is hired for six months to be his new caretaker. Worlds apart and trapped together by circumstance, the two get off to a rocky start. But the girl becomes determined to prove to the man that life is worth living and as they embark on a series of adventures together, each finds their world changing in ways neither of them could begin to imagine.",
  "rating": 7.926,
  "genres": [
    "Drama",
    "Romance"
  ],
  "images": [
    "still_0.webp",
    "still_2.webp"
  ],
  "slug": "me-before-you"
}