{
  "id": 39107,
  "title": "Dragon Ball Z: Fusion Reborn",
  "slug": "dragon-ball-z-fusion-reborn",
  "year": "1995",
  "overview": "Not paying attention to his job, a young demon allows the evil cleansing machine to overflow and explode, turning the young demon into the infamous monster Janemba. Goku and Vegeta make solo attempts to defeat the monster, but realize their only option is fusion.",
  "rating": 7.522,
  "genres": [
    "Animation",
    "Action",
    "Science Fiction"
  ],
  "images": [
    "still_0.webp",
    "still_1.webp"
  ],
  "original_title": "ドラゴンボールZ 復活のフュージョン!! 悟空とベジータ"
}