{
  "id": 144288,
  "title": "Berserk: The Golden Age Arc III - The Advent",
  "year": "2013",
  "overview": "One year has passed since Guts left the Band of the Hawk and Griffith was imprisoned by the Kingdom of Midland for treason. In the dead of night, at a camping site where they hide, the Band of the Hawk is attacked by Bakiraka assassins led by Silat. When all seems lost, Guts returns from his journey. \"You destroyed everything.\" Crying that Griffith is nothing without Guts, Casca and Guts are joined together body and soul. Griffith is imprisoned in the oldest building in Wyndham Catle, the Tower of Rebirth.",
  "rating": 7.6,
  "genres": [
    "Animation",
    "Action",
    "Adventure",
    "Drama",
    "Fantasy"
  ],
  "images": [
    "still_0.webp",
    "still_1.webp",
    "still_2.webp"
  ],
  "original_title": "ベルセルク 黄金時代篇Ⅲ 降臨"
}